simple_package/_init_.py
simple_package/dummy.py
myfirstdummypackage-0.1.2.dist-info/METADATA
myfirstdummypackage-0.1.2.dist-info/WHEEL
myfirstdummypackage-0.1.2.dist-info/top_level.txt
myfirstdummypackage-0.1.2.dist-info/RECORD
